Metadata-Version: 2.1
Name: streamlit-drawable-canvas-jsretry
Version: 0.9.3
Summary: A Streamlit custom component for a free drawing canvas using Fabric.js.  A fork to enable retrying for bg images.
Home-page: https://github.com/andfanilo/streamlit-drawable-canvas
Author: Vik Paruchuri
Author-email: github@vikas.sh
Requires-Python: >=3.6
License-File: LICENSE
Requires-Dist: Pillow
Requires-Dist: numpy
Requires-Dist: streamlit >=0.63
